{
    "profiles": [
        {
            "complex_modifications": {
                "rules": [
                    {
                        "manipulators": [
                            {
                                "description": "Hyper Key",
                                "from": {
                                    "key_code": "caps_lock",
                                    "modifiers": { "optional": ["any"] }
                                },
                                "to": [
                                    {
                                        "key_code": "right_shift",
                                        "modifiers": ["right_command", "right_control", "right_option"]
                                    }
                                ],
                                "type": "basic"
                            }
                        ]
                    }
                ]
            },
            "devices": [
                {
                    "fn_function_keys": [
                        {
                            "from": { "key_code": "f1" },
                            "to": [{ "key_code": "f1" }]
                        },
                        {
                            "from": { "key_code": "f2" },
                            "to": [{ "key_code": "f2" }]
                        },
                        {
                            "from": { "key_code": "f3" },
                            "to": [{ "key_code": "f3" }]
                        },
                        {
                            "from": { "key_code": "f4" },
                            "to": [{ "key_code": "f4" }]
                        },
                        {
                            "from": { "key_code": "f5" },
                            "to": [{ "key_code": "f5" }]
                        },
                        {
                            "from": { "key_code": "f6" },
                            "to": [{ "key_code": "f6" }]
                        },
                        {
                            "from": { "key_code": "f7" },
                            "to": [{ "key_code": "f7" }]
                        },
                        {
                            "from": { "key_code": "f8" },
                            "to": [{ "key_code": "f8" }]
                        },
                        {
                            "from": { "key_code": "f9" },
                            "to": [{ "key_code": "f9" }]
                        },
                        {
                            "from": { "key_code": "f10" },
                            "to": [{ "key_code": "f10" }]
                        },
                        {
                            "from": { "key_code": "f11" },
                            "to": [{ "key_code": "f11" }]
                        },
                        {
                            "from": { "key_code": "f12" },
                            "to": [{ "key_code": "f12" }]
                        }
                    ],
                    "identifiers": {
                        "is_keyboard": true,
                        "product_id": 291,
                        "vendor_id": 1046
                    }
                },
                {
                    "fn_function_keys": [
                        {
                            "from": { "key_code": "f1" },
                            "to": [{ "key_code": "f1" }]
                        },
                        {
                            "from": { "key_code": "f2" },
                            "to": [{ "key_code": "f2" }]
                        },
                        {
                            "from": { "key_code": "f3" },
                            "to": [{ "key_code": "f3" }]
                        },
                        {
                            "from": { "key_code": "f4" },
                            "to": [{ "key_code": "f4" }]
                        },
                        {
                            "from": { "key_code": "f5" },
                            "to": [{ "key_code": "f5" }]
                        },
                        {
                            "from": { "key_code": "f6" },
                            "to": [{ "key_code": "f6" }]
                        },
                        {
                            "from": { "key_code": "f7" },
                            "to": [{ "key_code": "f7" }]
                        },
                        {
                            "from": { "key_code": "f8" },
                            "to": [{ "key_code": "f8" }]
                        },
                        {
                            "from": { "key_code": "f9" },
                            "to": [{ "key_code": "f9" }]
                        },
                        {
                            "from": { "key_code": "f10" },
                            "to": [{ "key_code": "f10" }]
                        },
                        {
                            "from": { "key_code": "f11" },
                            "to": [{ "key_code": "f11" }]
                        },
                        {
                            "from": { "key_code": "f12" },
                            "to": [{ "key_code": "f12" }]
                        }
                    ],
                    "identifiers": {
                        "is_keyboard": true,
                        "product_id": 50495,
                        "vendor_id": 1133
                    }
                },
                {
                    "fn_function_keys": [
                        {
                            "from": { "key_code": "f1" },
                            "to": [{ "key_code": "f1" }]
                        },
                        {
                            "from": { "key_code": "f2" },
                            "to": [{ "key_code": "f2" }]
                        },
                        {
                            "from": { "key_code": "f3" },
                            "to": [{ "key_code": "f3" }]
                        },
                        {
                            "from": { "key_code": "f4" },
                            "to": [{ "key_code": "f4" }]
                        },
                        {
                            "from": { "key_code": "f5" },
                            "to": [{ "key_code": "f5" }]
                        },
                        {
                            "from": { "key_code": "f6" },
                            "to": [{ "key_code": "f6" }]
                        },
                        {
                            "from": { "key_code": "f7" },
                            "to": [{ "key_code": "f7" }]
                        },
                        {
                            "from": { "key_code": "f8" },
                            "to": [{ "key_code": "f8" }]
                        },
                        {
                            "from": { "key_code": "f9" },
                            "to": [{ "key_code": "f9" }]
                        },
                        {
                            "from": { "key_code": "f10" },
                            "to": [{ "key_code": "f10" }]
                        },
                        {
                            "from": { "key_code": "f11" },
                            "to": [{ "key_code": "f11" }]
                        },
                        {
                            "from": { "key_code": "f12" },
                            "to": [{ "key_code": "f12" }]
                        }
                    ],
                    "identifiers": {
                        "is_keyboard": true,
                        "product_id": 11446,
                        "vendor_id": 7805
                    }
                },
                {
                    "fn_function_keys": [
                        {
                            "from": { "key_code": "f1" },
                            "to": [{ "key_code": "f1" }]
                        },
                        {
                            "from": { "key_code": "f2" },
                            "to": [{ "key_code": "f2" }]
                        },
                        {
                            "from": { "key_code": "f3" },
                            "to": [{ "key_code": "f3" }]
                        },
                        {
                            "from": { "key_code": "f4" },
                            "to": [{ "key_code": "f4" }]
                        },
                        {
                            "from": { "key_code": "f5" },
                            "to": [{ "key_code": "f5" }]
                        },
                        {
                            "from": { "key_code": "f6" },
                            "to": [{ "key_code": "f6" }]
                        },
                        {
                            "from": { "key_code": "f7" },
                            "to": [{ "key_code": "f7" }]
                        },
                        {
                            "from": { "key_code": "f8" },
                            "to": [{ "key_code": "f8" }]
                        },
                        {
                            "from": { "key_code": "f9" },
                            "to": [{ "key_code": "f9" }]
                        },
                        {
                            "from": { "key_code": "f10" },
                            "to": [{ "key_code": "f10" }]
                        },
                        {
                            "from": { "key_code": "f11" },
                            "to": [{ "key_code": "f11" }]
                        },
                        {
                            "from": { "key_code": "f12" },
                            "to": [{ "key_code": "f12" }]
                        }
                    ],
                    "identifiers": {
                        "is_keyboard": true,
                        "product_id": 11505,
                        "vendor_id": 7805
                    }
                }
            ],
            "name": "Default profile"
        },
        {
            "complex_modifications": {
                "rules": [
                    {
                        "manipulators": [
                            {
                                "description": "Hyper Key",
                                "from": {
                                    "key_code": "caps_lock",
                                    "modifiers": { "optional": ["any"] }
                                },
                                "to": [
                                    {
                                        "key_code": "right_shift",
                                        "modifiers": ["right_command", "right_control", "right_option"]
                                    }
                                ],
                                "type": "basic"
                            }
                        ]
                    }
                ]
            },
            "devices": [
                {
                    "fn_function_keys": [
                        {
                            "from": { "key_code": "f1" },
                            "to": [{ "key_code": "f1" }]
                        },
                        {
                            "from": { "key_code": "f2" },
                            "to": [{ "key_code": "f2" }]
                        },
                        {
                            "from": { "key_code": "f3" },
                            "to": [{ "key_code": "f3" }]
                        },
                        {
                            "from": { "key_code": "f4" },
                            "to": [{ "key_code": "f4" }]
                        },
                        {
                            "from": { "key_code": "f5" },
                            "to": [{ "key_code": "f5" }]
                        },
                        {
                            "from": { "key_code": "f6" },
                            "to": [{ "key_code": "f6" }]
                        },
                        {
                            "from": { "key_code": "f7" },
                            "to": [{ "key_code": "f7" }]
                        },
                        {
                            "from": { "key_code": "f8" },
                            "to": [{ "key_code": "f8" }]
                        },
                        {
                            "from": { "key_code": "f9" },
                            "to": [{ "key_code": "f9" }]
                        },
                        {
                            "from": { "key_code": "f10" },
                            "to": [{ "key_code": "f10" }]
                        },
                        {
                            "from": { "key_code": "f11" },
                            "to": [{ "key_code": "f11" }]
                        },
                        {
                            "from": { "key_code": "f12" },
                            "to": [{ "key_code": "f12" }]
                        }
                    ],
                    "identifiers": {
                        "is_keyboard": true,
                        "product_id": 291,
                        "vendor_id": 1046
                    },
                    "simple_modifications": [
                        {
                            "from": { "key_code": "left_command" },
                            "to": [{ "key_code": "left_control" }]
                        },
                        {
                            "from": { "key_code": "left_control" },
                            "to": [{ "key_code": "left_command" }]
                        }
                    ]
                },
                {
                    "fn_function_keys": [
                        {
                            "from": { "key_code": "f1" },
                            "to": [{ "key_code": "f1" }]
                        },
                        {
                            "from": { "key_code": "f2" },
                            "to": [{ "key_code": "f2" }]
                        },
                        {
                            "from": { "key_code": "f3" },
                            "to": [{ "key_code": "f3" }]
                        },
                        {
                            "from": { "key_code": "f4" },
                            "to": [{ "key_code": "f4" }]
                        },
                        {
                            "from": { "key_code": "f5" },
                            "to": [{ "key_code": "f5" }]
                        },
                        {
                            "from": { "key_code": "f6" },
                            "to": [{ "key_code": "f6" }]
                        },
                        {
                            "from": { "key_code": "f7" },
                            "to": [{ "key_code": "f7" }]
                        },
                        {
                            "from": { "key_code": "f8" },
                            "to": [{ "key_code": "f8" }]
                        },
                        {
                            "from": { "key_code": "f9" },
                            "to": [{ "key_code": "f9" }]
                        },
                        {
                            "from": { "key_code": "f10" },
                            "to": [{ "key_code": "f10" }]
                        },
                        {
                            "from": { "key_code": "f11" },
                            "to": [{ "key_code": "f11" }]
                        },
                        {
                            "from": { "key_code": "f12" },
                            "to": [{ "key_code": "f12" }]
                        }
                    ],
                    "identifiers": {
                        "is_keyboard": true,
                        "product_id": 50495,
                        "vendor_id": 1133
                    }
                },
                {
                    "fn_function_keys": [
                        {
                            "from": { "key_code": "f1" },
                            "to": [{ "key_code": "f1" }]
                        },
                        {
                            "from": { "key_code": "f2" },
                            "to": [{ "key_code": "f2" }]
                        },
                        {
                            "from": { "key_code": "f3" },
                            "to": [{ "key_code": "f3" }]
                        },
                        {
                            "from": { "key_code": "f4" },
                            "to": [{ "key_code": "f4" }]
                        },
                        {
                            "from": { "key_code": "f5" },
                            "to": [{ "key_code": "f5" }]
                        },
                        {
                            "from": { "key_code": "f6" },
                            "to": [{ "key_code": "f6" }]
                        },
                        {
                            "from": { "key_code": "f7" },
                            "to": [{ "key_code": "f7" }]
                        },
                        {
                            "from": { "key_code": "f8" },
                            "to": [{ "key_code": "f8" }]
                        },
                        {
                            "from": { "key_code": "f9" },
                            "to": [{ "key_code": "f9" }]
                        },
                        {
                            "from": { "key_code": "f10" },
                            "to": [{ "key_code": "f10" }]
                        },
                        {
                            "from": { "key_code": "f11" },
                            "to": [{ "key_code": "f11" }]
                        },
                        {
                            "from": { "key_code": "f12" },
                            "to": [{ "key_code": "f12" }]
                        }
                    ],
                    "identifiers": {
                        "is_keyboard": true,
                        "product_id": 11446,
                        "vendor_id": 7805
                    }
                },
                {
                    "fn_function_keys": [
                        {
                            "from": { "key_code": "f1" },
                            "to": [{ "key_code": "f1" }]
                        },
                        {
                            "from": { "key_code": "f2" },
                            "to": [{ "key_code": "f2" }]
                        },
                        {
                            "from": { "key_code": "f3" },
                            "to": [{ "key_code": "f3" }]
                        },
                        {
                            "from": { "key_code": "f4" },
                            "to": [{ "key_code": "f4" }]
                        },
                        {
                            "from": { "key_code": "f5" },
                            "to": [{ "key_code": "f5" }]
                        },
                        {
                            "from": { "key_code": "f6" },
                            "to": [{ "key_code": "f6" }]
                        },
                        {
                            "from": { "key_code": "f7" },
                            "to": [{ "key_code": "f7" }]
                        },
                        {
                            "from": { "key_code": "f8" },
                            "to": [{ "key_code": "f8" }]
                        },
                        {
                            "from": { "key_code": "f9" },
                            "to": [{ "key_code": "f9" }]
                        },
                        {
                            "from": { "key_code": "f10" },
                            "to": [{ "key_code": "f10" }]
                        },
                        {
                            "from": { "key_code": "f11" },
                            "to": [{ "key_code": "f11" }]
                        },
                        {
                            "from": { "key_code": "f12" },
                            "to": [{ "key_code": "f12" }]
                        }
                    ],
                    "identifiers": {
                        "is_keyboard": true,
                        "product_id": 11505,
                        "vendor_id": 7805
                    }
                }
            ],
            "name": "Modifier Switch",
            "selected": true
        }
    ]
}